pystable/__init__.py
pystable/_extensions/__init__.py
pystable/_extensions/libstable.so
pystable/_extensions/linux/gclib-2-31/libstable.so
pystable/_extensions/linux/gclib-2-33/libstable.so
pystable/_extensions/macOS/arm/libstable.so
pystable/_extensions/macOS/i386/libstable.so
pystable/pystable.py
pystable/stable_dist.py
pystable/utils.py
pystable-0.2.3.dist-info/LICENSE
pystable-0.2.3.dist-info/WHEEL
pystable-0.2.3.dist-info/METADATA
pystable-0.2.3.dist-info/RECORD
