Metadata-Version: 2.1
Name: pystable
Version: 0.2.3
Summary: Python wrapper for the libstable C library
Home-page: https://github.com/overlay-market/pystable
License: GPL-3.0-only
Keywords: alpha stable,distribution,statistics,probability
Author: RJ Rybarczyk
Author-email: rj@rybar.tech
Requires-Python: >=3.9.5,<4.0.0
Classifier: License :: OSI Approved :: GNU General Public License v3 (GPLv3)
Classifier: Programming Language :: Python :: 3
Requires-Dist: setuptools (>=57.1.0,<58.0.0)
Project-URL: Repository, https://github.com/overlay-market/pystable
